wraparr/__init__.py
wraparr/base.py
wraparr/py.typed
wraparr/radarr.py
wraparr/sonarr.py
wraparr-0.2.11.dist-info/LICENSE
wraparr-0.2.11.dist-info/WHEEL
wraparr-0.2.11.dist-info/METADATA
wraparr-0.2.11.dist-info/RECORD
