Metadata-Version: 2.1
Name: wraparr
Version: 0.2.11
Summary: API wrapper for Radarr/Sonarr
Home-page: https://github.com/muqshots/wraparr
License: GPL-3.0-or-later
Keywords: sonarr,radarr,api,wrapper
Author: muqshots
Author-email: 82030029+muqshots@users.noreply.github.com
Requires-Python: >=3.10,<4.0
Classifier: License :: OSI Approved :: GNU General Public License v3 or later (GPLv3+)
Classifier: Programming Language :: Python :: 3
Classifier: Programming Language :: Python :: 3.10
Requires-Dist: httpx (>=0.20.0,<0.21.0)
Project-URL: Repository, https://github.com/muqshots/wraparr
